mpl_animators/__init__.py
mpl_animators/_version.py
mpl_animators/base.py
mpl_animators/image.py
mpl_animators/line.py
mpl_animators/version.py
mpl_animators/wcs.py
mpl_animators/data/README.rst
mpl_animators/extern/__init__.py
mpl_animators/extern/modest_image.py
mpl_animators/tests/__init__.py
mpl_animators/tests/figure_hashes_mpl_350_ft_261_astropy_53.json
mpl_animators/tests/figure_hashes_mpl_391_ft_261_astropy_611.json
mpl_animators/tests/figure_hashes_mpl_dev_ft_261_astropy_dev.json
mpl_animators/tests/helpers.py
mpl_animators/tests/test_basefuncanimator.py
mpl_animators/tests/test_wcs.py
mpl_animators-1.2.3.dist-info/licenses/LICENSE.rst
mpl_animators-1.2.3.dist-info/METADATA
mpl_animators-1.2.3.dist-info/WHEEL
mpl_animators-1.2.3.dist-info/top_level.txt
mpl_animators-1.2.3.dist-info/RECORD
