Metadata-Version: 2.4
Name: mpl_animators
Version: 1.2.3
Summary: An interactive animation framework for matplotlib.
Author-email: The SunPy Developers <sunpy@googlegroups.com>
License: Copyright (c) 2024, The SunPy Developers
Project-URL: Homepage, https://sunpy.org
Project-URL: Source Code, https://github.com/sunpy/mpl-animators
Project-URL: Download, https://pypi.org/project/mpl_animators
Project-URL: Documentation, https://docs.sunpy.org/projects/mpl-animators
Project-URL: Changelog, https://github.com/sunpy/mpl-animators/releases
Project-URL: Issue Tracker, https://github.com/sunpy/mpl-animators/issues
Requires-Python: >=3.10
License-File: LICENSE.rst
Requires-Dist: matplotlib>=3.5.0
Requires-Dist: numpy>=1.23.0
Provides-Extra: wcs
Requires-Dist: astropy>=5.3.0; extra == "wcs"
Provides-Extra: tests
Requires-Dist: pytest; extra == "tests"
Requires-Dist: pytest-doctestplus; extra == "tests"
Requires-Dist: pytest-cov; extra == "tests"
Requires-Dist: pytest-xdist; extra == "tests"
Requires-Dist: pytest-mpl; extra == "tests"
Provides-Extra: docs
Requires-Dist: sphinx; extra == "docs"
Requires-Dist: sphinx-automodapi; extra == "docs"
Requires-Dist: sphinx-changelog; extra == "docs"
Requires-Dist: sunpy-sphinx-theme; extra == "docs"
Requires-Dist: packaging; extra == "docs"
Requires-Dist: sphinx_gallery; extra == "docs"
Requires-Dist: sunpy; extra == "docs"
Requires-Dist: scipy; extra == "docs"
Provides-Extra: all
Requires-Dist: mpl_animators[wcs]; extra == "all"
Provides-Extra: dev
Requires-Dist: mpl_animators[all,docs,tests]; extra == "dev"
Dynamic: license-file
